QUINTAS_2HORAS/result/design.sv
module SHIFTER2D
  (	input wire	clk,reset,enable,
   input [7:0] ES,
   output wire [7:0] SS);
  
  
  reg [3:0][7:0] SHIFT;


  
always @(negedge reset, posedge clk)
if (!reset)
  SHIFT <= {4{8'h00}};
  else if (enable)
    begin
      // SHIFT<={ES,SHIFT[3:1]};
      SHIFT[3]<=ES;
      SHIFT[2]<=SHIFT[3];
      SHIFT[1]<=SHIFT[2];
      SHIFT[0]<=SHIFT[1];
    end

  assign SS=SHIFT[0];


tercera_prueba_despazamiento: assert property (@(posedge clk) disable iff(reset!==1'b1 ) enable[->4]  |=> SS==$past(ES,4,enable) ) else $info("AUTOCHEQUEO1: SS funciona incorrectamente");    


 
  
  endmodule

QUINTAS_2HORAS/result/testbench.sv
// Code your testbench here
// or browse Examples
`timescale 1 ns / 1 ps


module Shifter_basico_tb  ; 
localparam T=50;
localparam Thold=5;
localparam Td=10;
localparam Tsetup=5;
localparam Profundidad=4;
localparam tamanyo=8;
localparam Size=$clog2(Profundidad);

logic [7:0] out   ;
  
integer A;
reg aleatorio;

reg    clk   ; 
reg    reset   ; 
reg  [tamanyo-1:0]  in   ;
reg   enable;
  SHIFTER2D    DUT  ( 
     .SS (out ) ,
     .enable,
     .clk (clk  ) ,
     .reset (reset ) ,
     .ES (in ) ); 

initial begin clk = 1'b0;
forever #(T/2)  clk = !clk;
end

initial begin
  $dumpfile("SHIFTER2D.vcd");
  $dumpvars(0,Shifter_basico_tb);
end  
initial
begin
	$warning("SIMULANDO!!!"); 
    aleatorio=1'b0;
    reset=1'b1;
    enable=1'b0;
    in=8'b0;
	# (T*5);                    
  	$warning("VERIFICACION 1 desplazamiento de un UNO");     CASO_1(); 
 	#(T*5);
	aleatorio=1'b1;
  $warning("VERIFICACION 2 desplazamiento de otros 3 valores");CASO_2(); 
 	#(T*5);
  $warning("VERIFICACION 3 desplazamiento de otros 5 valores");CASO_3();
 	#(T*5);
    $stop;  
    $finish;
	end      

task resetea;
  	begin
      @(negedge clk) reset = 1'b0;
      enable=1'b1;
      @(negedge clk) reset  = 1'b1;
    end
endtask
  
always wait(aleatorio)
begin
                @(posedge clk)
	 	A = ({$random} % 2);
		#0 enable=A;
end

task CASO_1;
	begin
      resetea();
	  in=8'b1;
      enable=1'b1;
      @(negedge clk) in=8'b1;
      enable=1'b0;
      repeat (2) 	@(negedge clk);
      enable=1'b1; 
      repeat (2) 	@(negedge clk);  
      comprueba_vector_2pos(8'b1);
	end
endtask
task CASO_2;
	begin
      resetea();
	    in=8'b0;
      enable=1'b1;
      fork
        if (enable) estimula_y_comprueba(4,5);
        begin
        @(posedge clk);
        if (enable ) estimula_y_comprueba(4,7);
        end
        begin
          repeat(2)  @(posedge clk);
          if (enable )estimula_y_comprueba(4,48);
        end

      join
	end
endtask

task CASO_3;
   integer i;
	begin
      resetea();
      i=$random%8;
      fork
        if (enable) estimula_y_comprueba(4,i-1);
        begin
        @(posedge clk);
        if (enable ) estimula_y_comprueba(4,i);
        end
        begin
          repeat(2)  @(posedge clk);
          if (enable )estimula_y_comprueba(4,i+1);
        end
        begin
          repeat(3)  @(posedge clk);
          if (enable )estimula_y_comprueba(4,i+2);
        end
        begin
          repeat(4)  @(posedge clk);
          if (enable )estimula_y_comprueba(4,i+3);
        end

      join
	end
endtask 

task automatic comprueba_vector_neg;
ref  datos_sal_obtenido;
ref  reloj;  
input  datos_sal_esperado;
begin
  @(posedge reloj);
  @(negedge reloj);
  if(datos_sal_obtenido !== datos_sal_esperado)
    $error ("TEST: El shifter no da un retardo de 4 etapas");       
end
endtask  
  
  
task automatic comprueba_vector_2pos;
input  datos_sal_esperado;
begin
  @(posedge clk); 
  #(T-Tsetup);
  if(out !== datos_sal_esperado)
    $error ("TEST: El shifter no da un retardo de 4 etapas");       
  else 
       fork: espero_no_cambio
         @(out) $error ("fallo setup");
         @(posedge clk)  disable espero_no_cambio;                  
       join
end
endtask  
  
task automatic estimula_y_comprueba;
input int profundidad_shift;
input  [7: 0] dato_entrada_shift;

 automatic integer count;

       fork: espero
         count=0;      
         begin
             //@(posedge clk); 
                    #Thold in=dato_entrada_shift;
         end


         #0 begin 
           wait(count==profundidad_shift ); 
           #(T-Tsetup);
           if (out != dato_entrada_shift)
             $error ("TEST: El shifter no da un retardo de 4 etapas, da %d y debería dar %d",out,dato_entrada_shift );  
            else
              $info ("TEST: El shifter da un retardo de 4 etapas, da %d y debería dar %d",out,dato_entrada_shift ); 
         end
        while (count<profundidad_shift)
              begin 
                @(posedge clk);
                      if (enable==1'b1)
                          count=count+1;

              end
       join  

endtask  

endmodule

QUINTAS_2HORAS/result/SHIFTER2D.vcd
$date
	Tue Mar  4 03:43:25 2025
$end
$version
	QuestaSim Version 2024.3_1
$end
$timescale
	1ps
$end

$scope module Shifter_basico_tb $end

$scope module DUT $end
$var wire 1 ! ES [7] $end
$var wire 1 " ES [6] $end
$var wire 1 # ES [5] $end
$var wire 1 $ ES [4] $end
$var wire 1 % ES [3] $end
$var wire 1 & ES [2] $end
$var wire 1 ' ES [1] $end
$var wire 1 ( ES [0] $end
$var wire 1 ) SS [7] $end
$var wire 1 * SS [6] $end
$var wire 1 + SS [5] $end
$var wire 1 , SS [4] $end
$var wire 1 - SS [3] $end
$var wire 1 . SS [2] $end
$var wire 1 / SS [1] $end
$var wire 1 0 SS [0] $end
$var wire 1 1 clk $end
$var wire 1 2 enable $end
$var wire 1 3 reset $end
$var reg 32 4 SHIFT [31:0] $end

$scope begin tercera_prueba_despazamiento $end
$upscope $end
$upscope $end
$upscope $end
$enddefinitions $end
#0
$dumpvars
x0
x/
x.
x-
x,
x+
x*
x)
0(
0'
0&
0%
0$
0#
0"
0!
02
13
01
bx 4
$end
#25000
11
#50000
01
#75000
11
#100000
01
#125000
11
#150000
01
#175000
11
#200000
01
#225000
11
#250000
01
12
03
b0 4
00
0/
0.
0-
0,
0+
0*
0)
#275000
11
#300000
01
1(
13
#325000
11
b1000000000000000000000000 4
#350000
01
0(
02
#375000
11
#400000
01
#425000
11
#450000
01
12
#475000
11
b10000000000000000 4
#500000
01
#525000
11
b100000000 4
#550000
01
#575000
11
b1 4
10
#600000
01
#625000
11
b0 4
00
#650000
01
#675000
11
#700000
01
#725000
11
#750000
01
#775000
11
#800000
01
#825000
11
#850000
01
#875000
11
#900000
01
03
#925000
11
02
#950000
01
12
13
#975000
11
#1000000
01
#1025000
11
#1030000
1(
1&
#1050000
01
#1075000
11
b101000000000000000000000000 4
#1080000
1'
0&
#1100000
01
#1125000
11
b11000001010000000000000000 4
#1130000
0(
1&
#1150000
01
#1175000
11
b110000000110000010100000000 4
#1180000
1(
0'
0&
#1200000
01
#1225000
11
b1000001100000001100000101 4
10
1.
#1250000
01
#1275000
11
02
b1000000010000011000000011 4
1/
0.
#1280000
1&
#1300000
01
#1325000
11
12
#1350000
01
#1375000
11
b101000000010000000100000110 4
00
1.
#1400000
01
#1425000
11
02
b101000001010000000100000001 4
10
0/
0.
#1430000
0(
1'
#1450000
01
#1475000
11
12
#1500000
01
#1525000
11
b110000001010000010100000001 4
#1550000
01
#1575000
11
02
b110000001100000010100000101 4
1.
#1600000
01
#1625000
11
12
#1650000
01
#1675000
11
02
b110000001100000011000000101 4
