SEXTAS_HORAS/fsm_2024_mealy_2_procesos.v
module fsm_ones_mealy_2 (data_in, clk, reset, detect);
input data_in,clk,reset;
output reg detect; //tipo reg asignado dentro de un always

//binaria natural
reg [1:0] state;
parameter [1:0] S0=2'b00, S1=2'b01, S2=2'b10, S3=2'b11;



always@(posedge clk or negedge reset)
if (!reset)
    state<=S0;
else
    case (state) //caso que el estado actual es
    S0: if (data_in==1) state<=S1; else state<=S0; //el estado siguiente sera...
    S1: if (data_in==1) state<=S2; else state<=S0;
    S2: if (data_in==1) state<=S2; else state<=S0;
    default: state<=S0;
    endcase

//logica de las salidas MEALY
always@(state, data_in)
	case (state)
	S0: detect=0;
	S1: detect=0;
	S2: if (data_in) detect=1; else detect=0;
	default:detect=0;
	endcase
	
endmodule

SEPTIMAS_HORAS/fsm_2024_Moore_1_proceso.v
module fsm_ones_moore_2 (data_in, clk, reset, detect);
input data_in,clk,reset;
output reg detect; //tipo reg asignado dentro de un always

//binaria natural
reg [1:0] state;

parameter [1:0] S0=2'b00, S1=2'b01, S2=2'b10, S3=2'b11;

//definimos la logica del estado siguiente
always@(posedge clk or negedge reset)
if (!reset)
begin
	state<=S0;
	detect<=0;
end
else 
	begin
		detect<=0;
		case (state) //caso que el estado actual es
		S0: if (data_in==1) state<=S1; else state<=S0; //el estado siguiente sera...
		S1: if (data_in==1) state<=S2; else state<=S0;
		S2: if (data_in==1) begin state<=S3; detect<=1;end else state<=S0;
		S3: if (data_in==1) begin state<=S3; detect<=1;end else state<=S0;
		default: state<=S0;
		endcase
	end




endmodule

SEXTAS_HORAS/FSM_ones_tb_mealy_moore.v
/* test bench fsm detector de unos */

// definicion de unidad de tiempo/resolucion

`timescale 1 ns/ 100 ps

module tb_fsm_ones();
// definicion de periodo de reloj
localparam T=20;

reg CLK;
reg SECUENCIA_INPUT;
reg RST;
  
wire DETECCION_moore, DETECCION_mealy;

event DET;
always@(DET)
	$display("Caso de Test finalizado\n");

// DUV

fsm_ones_moore_2 DUV_moore
(
	.data_in(SECUENCIA_INPUT) ,	
	.clk(CLK) ,	
	.reset(RST) ,	
	.detect(DETECCION_moore) 	
);

fsm_ones_mealy_2 DUV_mealy
(
	.data_in(SECUENCIA_INPUT) ,	
	.clk(CLK) ,	
	.reset(RST) ,	
	.detect(DETECCION_mealy) 	
);


// DEFINICION DE TEST DE RESET
task RESET();
begin
// Reset de dos ciclos (asincrono)
	RST=1'b0;
	repeat(2) @(negedge CLK);
// Desactivamos el reset
	RST=1'b1;
end
endtask

// DEFINICION DEL RELOJ
always
begin
	#(T/2) CLK = ~CLK;
end



initial                                                
begin
//inicializacion de senales                                               
	CLK=0;
	SECUENCIA_INPUT=0;
	RST=0;
    $dumpfile("fsm_ones_mealy_moore.vcd");
    $dumpvars(0,tb_fsm_ones);

//casos de test
	RESET();
	CASO_1();->DET;
	repeat(5) @(negedge CLK);

	RESET();
	CASO_2();->DET;
	repeat(5) @(negedge CLK);

	RESET();
	CASO_3();->DET;
	repeat(5) @(negedge CLK);
	
	RESET();
	CASO_4();->DET;
	repeat(5) @(negedge CLK);
	
	RESET();
	CASO_5();->DET;
	repeat(5) @(negedge CLK);
	
	$display("Fin de simulacion!!");
	$stop;
end                                                    

task CASO_1();
	// se introducen tres unos seguidos
begin
repeat (3)
	begin
	@(negedge CLK);
	SECUENCIA_INPUT=1'b1;
	end
//terminamos caso poniendo entrada a cero
cero();
end
endtask

task CASO_2();
begin
	// Se introducen mas de tres unos seguidos
repeat(6)
	begin
	@(negedge CLK);
	SECUENCIA_INPUT=1'b1;
	end
	//terminamos caso poniendo entrada a cero
	cero();
end
endtask

task CASO_3();
begin
	// Se introducen 110
repeat(2)
	begin
	@(negedge CLK);
	SECUENCIA_INPUT=1'b1;
	end
@(negedge CLK);
SECUENCIA_INPUT=1'b0;

//terminamos caso poniendo entrada a cero
cero();
end
endtask

task CASO_4();
//se introducen 10101010
begin
	repeat(4)
	begin
	@(negedge CLK);
	SECUENCIA_INPUT=1'b1;
	@(negedge CLK);
	SECUENCIA_INPUT=1'b0;
	end

//terminamos caso poniendo entrada a cero
cero();

end
endtask

task CASO_5();
//introducimos 1101110110
begin
	uno();
	uno();
	cero();
	repeat(3) uno();
	cero();
	repeat(2) uno();
	cero();
end
endtask

task uno();
begin	
	@(negedge CLK);
	SECUENCIA_INPUT=1'b1;
end
endtask

task cero();
begin
	@(negedge CLK);
	SECUENCIA_INPUT=1'b0;
end
endtask

	
endmodule

SEPTIMAS_HORAS/fsm_ones_mealy_moore.vcd
$date
	Wed Apr 24 11:39:22 2024
$end
$version
	Questa Intel Starter FPGA Edition Version 2021.2
$end
$timescale
	100ps
$end

$scope module tb_fsm_ones $end
$var parameter 32 ! T $end
$var reg 1 " CLK $end
$var reg 1 # SECUENCIA_INPUT $end
$var reg 1 $ RST $end
$var wire 1 % DETECCION_moore $end
$var wire 1 & DETECCION_mealy $end
$var event 1 ' DET $end

$scope task RESET $end
$upscope $end

$scope task CASO_1 $end
$upscope $end

$scope task CASO_2 $end
$upscope $end

$scope task CASO_3 $end
$upscope $end

$scope task CASO_4 $end
$upscope $end

$scope task CASO_5 $end
$upscope $end

$scope task uno $end
$upscope $end

$scope task cero $end
$upscope $end

$scope module DUV_moore $end
$var parameter 2 ( S0 $end
$var parameter 2 ) S1 $end
$var parameter 2 * S2 $end
$var parameter 2 + S3 $end
$var wire 1 , data_in $end
$var wire 1 - clk $end
$var wire 1 . reset $end
$var reg 1 / detect $end
$var reg 2 0 state [1:0] $end
$upscope $end

$scope module DUV_mealy $end
$var parameter 2 1 S0 $end
$var parameter 2 2 S1 $end
$var parameter 2 3 S2 $end
$var parameter 2 4 S3 $end
$var wire 1 5 data_in $end
$var wire 1 6 clk $end
$var wire 1 7 reset $end
$var reg 1 8 detect $end
$var reg 2 9 state [1:0] $end
$upscope $end
$upscope $end
$enddefinitions $end
#0
$dumpvars
0"
0#
0$
0/
b0 0
08
b0 9
b10100 !
b0 (
b1 )
b10 *
b11 +
b0 1
b1 2
b10 3
b11 4
1'
0%
0&
07
06
05
0.
0-
0,
$end
#100
1"
1-
16
#200
0"
0-
06
#300
1"
1-
16
#400
0"
0-
06
1$
1.
17
#500
1"
1-
16
#600
0"
0-
06
1#
1,
15
#700
1"
1-
16
b1 9
b1 0
#800
0"
0-
06
#900
1"
1-
16
b10 9
b10 0
18
1&
#1000
0"
0-
06
#1100
1"
1-
16
b11 0
1/
1%
#1200
0"
0-
06
0#
1'
0,
05
08
0&
#1300
1"
1-
16
b0 9
b0 0
0/
0%
#1400
0"
0-
06
#1500
1"
1-
16
#1600
0"
0-
06
#1700
1"
1-
16
#1800
0"
0-
06
#1900
1"
1-
16
#2000
0"
0-
06
#2100
1"
1-
16
#2200
0"
0-
06
0$
0.
07
#2300
1"
1-
16
#2400
0"
0-
06
#2500
1"
1-
16
#2600
0"
0-
06
1$
1.
17
#2700
1"
1-
16
#2800
0"
0-
06
1#
1,
15
#2900
1"
1-
16
b1 9
b1 0
#3000
0"
0-
06
#3100
1"
1-
16
b10 9
b10 0
18
1&
#3200
0"
0-
06
#3300
1"
1-
16
b11 0
1/
1%
#3400
0"
0-
06
#3500
1"
1-
16
#3600
0"
0-
06
#3700
1"
1-
16
#3800
0"
0-
06
#3900
1"
1-
16
#4000
0"
0-
06
0#
1'
0,
05
08
0&
#4100
1"
1-
16
b0 9
b0 0
0/
0%
#4200
0"
0-
06
#4300
1"
1-
16
#4400
0"
0-
06
#4500
1"
1-
16
#4600
0"
0-
06
#4700
1"
1-
16
#4800
0"
0-
06
#4900
1"
1-
16
#5000
0"
0-
06
0$
0.
07
#5100
1"
1-
16
#5200
0"
0-
06
#5300
1"
1-
16
#5400
0"
0-
06
1$
1.
17
#5500
1"
1-
16
#5600
0"
0-
06
1#
1,
15
#5700
1"
1-
16
b1 9
b1 0
#5800
0"
0-
06
#5900
1"
1-
16
b10 9
b10 0
18
1&
#6000
0"
0-
06
0#
0,
05
08
0&
#6100
1"
1-
16
b0 9
b0 0
#6200
0"
0-
06
1'
#6300
1"
1-
16
#6400
0"
0-
06
#6500
1"
1-
16
#6600
0"
0-
06
#6700
1"
1-
16
#6800
0"
0-
06
#6900
1"
1-
16
#7000
0"
0-
06
#7100
1"
1-
16
#7200
0"
0-
06
0$
0.
07
#7300
1"
1-
16
#7400
0"
0-
06
#7500
1"
1-
16
#7600
0"
0-
06
1$
1.
17
#7700
1"
1-
16
#7800
0"
0-
06
1#
1,
15
#7900
1"
1-
16
b1 9
b1 0
#8000
0"
0-
06
0#
0,
05
#8100
1"
1-
16
b0 9
b0 0
#8200
0"
0-
06
1#
1,
15
#8300
1"
1-
16
b1 9
b1 0
#8400
0"
0-
06
0#
0,
05
#8500
1"
1-
16
b0 9
b0 0
#8600
0"
0-
06
1#
1,
15
#8700
1"
1-
16
b1 9
b1 0
#8800
0"
0-
06
0#
0,
05
#8900
1"
1-
16
b0 9
b0 0
#9000
0"
0-
06
1#
1,
15
#9100
1"
1-
16
b1 9
b1 0
#9200
0"
0-
06
0#
0,
05
#9300
1"
1-
16
b0 9
b0 0
#9400
0"
0-
06
1'
#9500
1"
1-
16
#9600
0"
0-
06
#9700
1"
1-
16
#9800
0"
0-
06
#9900
1"
1-
16
#10000
0"
0-
06
#10100
1"
1-
16
#10200
0"
0-
06
#10300
1"
1-
16
#10400
0"
0-
06
0$
0.
07
#10500
1"
1-
16
#10600
0"
0-
06
#10700
1"
1-
16
#10800
0"
0-
06
1$
1.
17
#10900
1"
1-
16
#11000
0"
0-
06
1#
1,
15
#11100
1"
1-
16
b1 9
b1 0
#11200
0"
0-
06
#11300
1"
1-
16
b10 9
b10 0
18
1&
#11400
0"
0-
06
0#
0,
05
08
0&
#11500
1"
1-
16
b0 9
b0 0
#11600
0"
0-
06
1#
1,
15
#11700
1"
1-
16
b1 9
b1 0
#11800
0"
0-
06
#11900
1"
1-
16
b10 9
b10 0
18
1&
#12000
0"
0-
06
#12100
1"
1-
16
b11 0
1/
1%
#12200
0"
0-
06
0#
0,
05
08
0&
#12300
1"
1-
16
b0 9
b0 0
0/
0%
#12400
0"
0-
06
1#
1,
15
#12500
1"
1-
16
b1 9
b1 0
#12600
0"
0-
06
#12700
1"
1-
16
b10 9
b10 0
18
1&
#12800
0"
0-
06
0#
1'
0,
05
08
0&
#12900
1"
1-
16
b0 9
b0 0
