TERCERAS_2HORAS/flip_flop_D_1.v
module DFF_1 (q,qb,clk,d,clear);
input clk,d,clear;
output q,qb;
reg q, qb; 

always @(posedge clk)
    if (clear!=0)
	begin	
	      #8 q=  d;
	      #1 qb= ~q;
    end
always wait (clear==0)
begin
	#4 q=0;
	#1 qb= 1;
	wait (clear==1);
end
endmodule

TERCERAS_2HORAS/tb_dff1.v

module DFF_tb_1;

  // Parameters

  //Ports
  reg  clk;
  reg  d;
  reg  clear;
  wire  q;
  wire  qb;

  DFF_1  DFF_inst (
    .clk(clk),
    .d(d),
    .clear(clear),
    .q(q),
    .qb(qb)
  );

always #5  clk = ! clk ;

initial begin
  $dumpfile("DFF_tb_1.vcd");
  $dumpvars(0,DFF_tb_1);
  clk = 0;
  d = 0;
  clear = 1;
    #10 d = 1;
    #10 d = 0;
    #10 d = 1;
    #10 d = 0;
    #10 d = 1;
#10 clear = 0;
#10 clear = 1;   
#100 $finish;
end

  //Initializations
  initial begin
    $monitor("clk=%b d=%b clear=%b q=%b qb=%b",clk,d,clear,q,qb); 
end
endmodule

TERCERAS_2HORAS/DFF_tb_1.vcd
$date
	Wed Feb 28 11:18:29 2024
$end
$version
	QuestaSim Version 2020.2
$end
$timescale
	1ns
$end

$scope module DFF_tb_1 $end
$var reg 1 ! clk $end
$var reg 1 " d $end
$var reg 1 # clear $end
$var wire 1 $ q $end
$var wire 1 % qb $end

$scope module DFF_inst $end
$var wire 1 & clk $end
$var wire 1 ' d $end
$var wire 1 ( clear $end
$var reg 1 ) q $end
$var reg 1 * qb $end
$upscope $end
$upscope $end
$enddefinitions $end
#0
$dumpvars
0!
0"
1#
x)
x*
x$
x%
1(
0'
0&
$end
#5
1!
1&
#10
1"
0!
1'
0&
#13
1)
1$
#14
0*
0%
#15
1!
1&
#20
0"
0!
0'
0&
#23
0)
0$
#24
1*
1%
#25
1!
1&
#30
1"
0!
1'
0&
#33
1)
1$
#34
0*
0%
#35
1!
1&
#40
0"
0!
0'
0&
#43
0)
0$
#44
1*
1%
#45
1!
1&
#50
1"
0!
1'
0&
#53
1)
1$
#54
0*
0%
#55
1!
1&
#60
0#
0!
0(
0&
#64
0)
1*
0$
1%
#65
1!
1&
#70
1#
0!
1(
0&
#75
1!
1&
#80
0!
0&
#83
1)
1$
#84
0*
0%
