TERCERAS_2HORAS/flip_flop_D_2.v
module DFF_2 (q,qb,clk,d,clear);
input clk,d,clear;
output q,qb;
reg q, qb; 

always @(posedge clk)
    if (clear!=0)
	begin	
	      q= #8  d;
	      qb=#1 ~q;
    end
always wait (clear==0)
begin
	#4 q=0;
	#1 qb= 1;
	wait (clear==1);
end
endmodule

TERCERAS_2HORAS/tb_dff2.v

module DFF_tb_2;

  // Parameters

  //Ports
  reg  clk;
  reg  d;
  reg  clear;
  wire  q;
  wire  qb;

  DFF_2  DFF_inst (
    .clk(clk),
    .d(d),
    .clear(clear),
    .q(q),
    .qb(qb)
  );

always #5  clk = ! clk ;

initial begin
  $dumpfile("DFF_tb_2.vcd");
  $dumpvars(0,DFF_tb_2);
  clk = 0;
  d = 0;
  clear = 1;
    #10 d = 1;
    #10 d = 0;
    #10 d = 1;
    #10 d = 0;
    #10 d = 1;
#10 clear = 0;
#10 clear = 1;   
#100 $finish;
end

  //Initializations
  initial begin
    $monitor("clk=%b d=%b clear=%b q=%b qb=%b",clk,d,clear,q,qb); 
end
endmodule

TERCERAS_2HORAS/DFF_tb_2.vcd
$date
	Wed Feb 28 11:13:25 2024
$end
$version
	QuestaSim Version 2020.2
$end
$timescale
	1ns
$end

$scope module DFF_tb_2 $end
$var reg 1 ! clk $end
$var reg 1 " d $end
$var reg 1 # clear $end
$var wire 1 $ q $end
$var wire 1 % qb $end

$scope module DFF_inst $end
$var wire 1 & clk $end
$var wire 1 ' d $end
$var wire 1 ( clear $end
$var reg 1 ) q $end
$var reg 1 * qb $end
$upscope $end
$upscope $end
$enddefinitions $end
#0
$dumpvars
0!
0"
1#
x)
x*
x$
x%
1(
0'
0&
$end
#5
1!
1&
#10
1"
0!
1'
0&
#13
0)
0$
#14
1*
1%
#15
1!
1&
#20
0"
0!
0'
0&
#23
1)
1$
#24
0*
0%
#25
1!
1&
#30
1"
0!
1'
0&
#33
0)
0$
#34
1*
1%
#35
1!
1&
#40
0"
0!
0'
0&
#43
1)
1$
#44
0*
0%
#45
1!
1&
#50
1"
0!
1'
0&
#53
0)
0$
#54
1*
1%
#55
1!
1&
#60
0#
0!
0(
0&
#63
1)
1$
#64
0)
0*
0$
0%
#65
1!
1*
1%
1&
#70
1#
0!
1(
0&
#75
1!
1&
#80
0!
0&
#83
1)
1$
#84
0*
0%
