TERCERAS_2HORAS/flip_flop_D_3.v
module DFF_3 (q,qb,clk,d,clear);
input clk,d,clear;
output q,qb;
reg q, qb; 

always @(posedge clk)
    if (clear!=0)
	begin	
	      q <= #8  d;
	      qb<= #1 ~q;
    end
always wait (clear==0)
begin
	#4 q=0;
	#1 qb= 1;
	wait (clear==1);
end
endmodule

TERCERAS_2HORAS/tb_dff3.v

module DFF_tb_3;

  // Parameters

  //Ports
  reg  clk;
  reg  d;
  reg  clear;
  wire  q;
  wire  qb;

  DFF_3  DFF_inst (
    .clk(clk),
    .d(d),
    .clear(clear),
    .q(q),
    .qb(qb)
  );

always #5  clk = ! clk ;

initial begin
  $dumpfile("DFF_tb_3.vcd");
  $dumpvars(0,DFF_tb_3);
  clk = 0;
  d = 0;
  clear = 1;
    #10 d = 1;
    #10 d = 0;
    #10 d = 1;
    #10 d = 0;
    #10 d = 1;
#10 clear = 0;
#10 clear = 1;   
#100 $finish;
end

  //Initializations
  initial begin
    $monitor("clk=%b d=%b clear=%b q=%b qb=%b",clk,d,clear,q,qb); 
end
endmodule

TERCERAS_2HORAS/DFF_tb_3.vcd
$date
	Wed Feb 28 11:44:55 2024
$end
$version
	QuestaSim Version 2020.2
$end
$timescale
	1ns
$end

$scope module DFF_tb_3 $end
$var reg 1 ! clk $end
$var reg 1 " d $end
$var reg 1 # clear $end
$var wire 1 $ q $end
$var wire 1 % qb $end

$scope module DFF_inst $end
$var wire 1 & clk $end
$var wire 1 ' d $end
$var wire 1 ( clear $end
$var reg 1 ) q $end
$var reg 1 * qb $end
$upscope $end
$upscope $end
$enddefinitions $end
#0
$dumpvars
0!
0"
1#
x)
x*
x$
x%
1(
0'
0&
$end
#5
1!
1&
#10
1"
0!
1'
0&
#13
0)
0$
#15
1!
1&
#16
1*
1%
#20
0"
0!
0'
0&
#23
1)
1$
#25
1!
1&
#26
0*
0%
#30
1"
0!
1'
0&
#33
0)
0$
#35
1!
1&
#36
1*
1%
#40
0"
0!
0'
0&
#43
1)
1$
#45
1!
1&
#46
0*
0%
#50
1"
0!
1'
0&
#53
0)
0$
#55
1!
1&
#56
1*
1%
#60
0#
0!
0(
0&
#63
1)
1$
#64
0)
0$
#65
1!
1&
#70
1#
0!
1(
0&
#75
1!
1&
#80
0!
0&
#83
1)
1$
#85
1!
1&
#86
0*
0%
