SEGUNDAS_2HORAS/flip_flop_D_2_best.v
module DFF_2 (q,qb,clk,d,clear);
input clk,d,clear;
output q,qb;
reg q, qb; 

always @(posedge clk)
    if (clear!=0)
	begin: sincrono	
	      q= #8 d;
	      qb=#1 ~q;
    end
always wait (clear==0)
begin
    disable sincrono;
	#4 q=0;
	#1 qb= 1;
	wait (clear==1);
end
endmodule

SEGUNDAS_2HORAS/tb_flip_flop_D.v

module DFF_tb;

  // Parameters

  //Ports
  reg  clk;
  reg  d;
  reg  clear;
  wire  q;
  wire  qb;

  DFF_2  DFF_inst (
    .clk(clk),
    .d(d),
    .clear(clear),
    .q(q),
    .qb(qb)
  );

always #5  clk = ! clk ;

initial begin
  $dumpfile("DFF_tb2.vcd");
  $dumpvars(0, DFF_tb);
  #100 $finish;
end
initial begin
  clk = 0;
  d = 1;
  clear = 1;
  #7 clear = 0;
  #10   d = 0;
  #6  clear=1;
  #17 d=1;
  #7 d=0;  
end



endmodule

SEGUNDAS_2HORAS/DFF_tb.vcd
$date
	Wed Feb 12 12:25:04 2025
$end
$version
	QuestaSim Version 2024.3
$end
$timescale
	1ns
$end

$scope module DFF_tb $end
$var reg 1 ! clk $end
$var reg 1 " d $end
$var reg 1 # clear $end
$var wire 1 $ q $end
$var wire 1 % qb $end

$scope module DFF_inst $end
$var wire 1 & clk $end
$var wire 1 ' d $end
$var wire 1 ( clear $end
$var reg 1 ) q $end
$var reg 1 * qb $end
$upscope $end
$upscope $end
$enddefinitions $end
#0
$dumpvars
0!
1"
1#
x)
x*
x$
x%
1(
1'
0&
$end
#5
1!
1&
#7
0#
0(
#10
0!
0&
#11
0)
0$
#12
1*
1%
#13
1)
1$
#14
0*
0%
#15
1!
1&
#17
0"
0'
#20
0!
0&
#23
1#
1(
#25
1!
1&
#30
0!
0&
#33
0)
0$
#34
1*
1%
#35
1!
1&
#40
1"
0!
1'
0&
#43
1)
1$
#44
0*
0%
#45
1!
1&
#47
0"
0'
#50
0!
0&
#53
0)
0$
#54
1*
1%
