SEGUNDAS_2HORAS/flip_flop_D_RTL.v
module DFF (q,qb,clk,d,clear);
input clk,d,clear;
output q,qb;
reg q;
wire qb; 

always @(posedge clk, negedge clear)
    if (clear==1'b0)
    begin
        #4 q= 1'b0;

    end
    else
        begin	
            #8 q=d;

        end
assign qb = ~q;

endmodule

SEGUNDAS_2HORAS/tb_flip_flop_D.v

module DFF_tb;

  // Parameters

  //Ports
  reg  clk;
  reg  d;
  reg  clear;
  wire  q;
  wire  qb;

  DFF  DFF_inst (
    .clk(clk),
    .d(d),
    .clear(clear),
    .q(q),
    .qb(qb)
  );

always #5  clk = ! clk ;

initial begin
  $dumpfile("DFF_tb.vcd");
  $dumpvars(1, DFF_tb);
  #100 $finish;
end
initial begin
  clk = 0;
  d = 1;
  clear = 1;
  #7 clear = 0;
  #10   d = 0;
  #6  clear=1;
  #17 d=1;
  #7 d=0;  
end



endmodule

SEGUNDAS_2HORAS/DFF_tb.vcd
$date
	Wed Feb 21 13:22:48 2024
$end
$version
	QuestaSim Version 2020.2
$end
$timescale
	1ns
$end

$scope module DFF_tb $end
$var reg 1 ! clk $end
$var reg 1 " d $end
$var reg 1 # clear $end
$var wire 1 $ q $end
$var wire 1 % qb $end
$upscope $end
$enddefinitions $end
#0
$dumpvars
0!
1"
1#
x$
x%
$end
#5
1!
#7
0#
#10
0!
#11
0$
#12
1%
#13
1$
#14
0%
#15
1!
#17
0"
#20
0!
#23
1#
#25
1!
#30
0!
#33
0$
#34
1%
#35
1!
#40
1"
0!
#45
1!
#47
0"
#50
0!
#53
1$
#54
0%
#55
1!
#60
0!
#63
0$
#64
1%
