SEGUNDAS_2HORAS/flip_flop_D_2_best.v
module DFF_2 (q,qb,clk,d,clear);
input clk,d,clear;
output q,qb;
reg q, qb; 

always @(posedge clk)
    if (clear!=0)
	begin: sincrono	
	      q= #8 d;
	      qb=#1 ~q;
    end
always wait (clear==0)
begin
    disable sincrono;
	#4 q=0;
	#1 qb= 1;
	wait (clear==1);
end
endmodule

SEGUNDAS_2HORAS/tb_flip_flop_D.v

module DFF_tb;

  // Parameters

  //Ports
  reg  clk;
  reg  d;
  reg  clear;
  wire  q;
  wire  qb;

  DFF_2  DFF_inst (
    .clk(clk),
    .d(d),
    .clear(clear),
    .q(q),
    .qb(qb)
  );

always #5  clk = ! clk ;

initial begin
  $dumpfile("DFF_tb2.vcd");
  $dumpvars(0, DFF_tb);
  #100 $finish;
end
initial begin
  clk = 0;
  d = 1;
  clear = 1;
  #7 clear = 0;
  #10   d = 0;
  #6  clear=1;
  #17 d=1;
  #7 d=0;  
end



endmodule

OCTAVAS_HORAS/contador_basico.v/DFF_tb.vcd
$date
	Fri Sep  6 10:12:08 2024
$end
$version
	QuestaSim Version 2023.4
$end
$timescale
	1ns
$end

$scope module DFF_tb $end
$var wire 1 ! q $end
$var wire 1 " qb $end
$var reg 1 # clear $end
$var reg 1 $ clk $end
$var reg 1 % d $end

$scope module DFF_inst $end
$var wire 1 # clear $end
$var wire 1 $ clk $end
$var wire 1 % d $end
$var reg 1 ! q $end
$var reg 1 " qb $end
$upscope $end
$upscope $end
$enddefinitions $end
#0
$dumpvars
1#
0$
1%
x!
x"
$end
#5
1$
#7
0#
#10
0$
#11
0!
#12
1"
#13
1!
#14
0"
#15
1$
#17
0%
#20
0$
#23
1#
#25
1$
#30
0$
#33
0!
#34
1"
#35
1$
#40
1%
0$
#45
1$
#47
0%
#50
0$
#53
1!
#54
0"
#55
1$
#60
0$
#63
0!
#64
1"
