CUARTAS_2HORAS/AND_OR_INVERT_2.v
module and_or_invert_2(
    input A,
    input B,
    input C,
    input D, 
    output reg TZ
    );
    reg TM, TN, TO;
    always @(A,B,C,D) begin
        TM <= A & B ;
        TN <= C & D;
        TO <= TM | TN;
        TZ <= ~TO;
    end
    
endmodule

CUARTAS_2HORAS/AND_OR_INVERT_1.v
module and_or_invert_1(
    input A,
    input B,
    input C,
    input D, 
    output reg TZ
    );
    reg TM, TN, TO;
    always @(A,B,C,D) begin
        TM = A & B;
        TN = C & D;
        TO = TM | TN;
        TZ = ~TO;
    end
    
endmodule

CUARTAS_2HORAS/tb_and_or_invert.v
`timescale 1ns / 1ps
module and_or_invert_1_tb;

  // Parameters

  //Ports
  reg  A;
  reg  B;
  reg  C;
  reg  D;
  wire  TZ1, TZ2;


  and_or_invert_1  and_or_invert_1_inst (
    .A(A),
    .B(B),
    .C(C),
    .D(D),
    .TZ(TZ1)
  );

  and_or_invert_2  and_or_invert_2_inst (
    .A(A),
    .B(B),
    .C(C),
    .D(D),
    .TZ(TZ2)
  );
//crear combinaciones de A,B,C,D
    initial begin
        A = 0;
        B = 0;
        C = 0;
        D = 0;
        #5  A = 1;
        #5  B = 1;
        #5  C = 1;
        #5  D = 1;
        #5  A = 0;
        #5  B = 0;
        #5  C = 0;
        #5  D = 0;
        #5  $finish;
    end 
    initial begin
        $dumpfile("and_or_invert_1_tb.vcd");
        $dumpvars(0, and_or_invert_1_tb);
    end
//always #5  clk = ! clk ;
    //initial para monitorizar
    initial begin
        $monitor("A=%b B=%b C=%b D=%b TZ1=%b TZ2=%b", A, B, C, D, TZ1, TZ2); 
    end 

always 
//display time
    begin: monitor
        wait(TZ1!==TZ2);
        $display("Error las salidas son diferentes en tiempo %0t ns: TZ1=%b TZ2=%b", $realtime/1e3,TZ1, TZ2);
        @(TZ1,TZ2);
    end

endmodule

CUARTAS_2HORAS/and_or_invert_1_tb copy.vcd
$date
	Wed Mar 06 10:07:06 2024
$end
$version
	QuestaSim Version 2020.2
$end
$timescale
	1ns
$end

$scope module and_or_invert_1_tb $end
$var reg 1 ! A $end
$var reg 1 " B $end
$var reg 1 # C $end
$var reg 1 $ D $end
$var wire 1 % TZ1 $end
$var wire 1 & TZ2 $end

$scope module and_or_invert_1_inst $end
$var wire 1 ' A $end
$var wire 1 ( B $end
$var wire 1 ) C $end
$var wire 1 * D $end
$var reg 1 + TZ $end
$var reg 1 , TM $end
$var reg 1 - TN $end
$var reg 1 . TO $end
$upscope $end

$scope module and_or_invert_2_inst $end
$var wire 1 / A $end
$var wire 1 0 B $end
$var wire 1 1 C $end
$var wire 1 2 D $end
$var reg 1 3 TZ $end
$var reg 1 4 TM $end
$var reg 1 5 TN $end
$var reg 1 6 TO $end
$upscope $end
$upscope $end
$enddefinitions $end
#0
$dumpvars
0!
0"
0#
0$
1+
0,
0-
0.
x3
04
05
x6
1%
x&
02
01
00
0/
0*
0)
0(
0'
$end
#5
1!
1'
1/
06
#10
1"
1(
10
1,
1.
0+
0%
14
13
1&
#15
1#
1)
11
16
#20
1$
1*
12
1-
15
03
0&
#25
0!
0'
0/
0,
04
#30
0"
0(
00
#35
0#
0)
01
0-
0.
1+
1%
05
#40
0$
0*
02
06
